cleaningbox/__init__.py
cleaningbox/__main__.py
cleaningbox/binarization.py
cleaningbox/core.py
cleaningbox/imputation.py
cleaningbox/normalization.py
cleaningbox/one_hot_encoding.py
cleaningbox/outlier_detection.py
cleaningbox-1.0.3.dist-info/licenses/LICENSE
cleaningbox-1.0.3.dist-info/METADATA
cleaningbox-1.0.3.dist-info/WHEEL
cleaningbox-1.0.3.dist-info/top_level.txt
cleaningbox-1.0.3.dist-info/RECORD
