Metadata-Version: 2.4
Name: cleaningbox
Version: 1.0.3
Summary: A lightweight, modular Python library for data cleaning workflows.
Home-page: https://github.com/knochez/cleaningbox
Author: Kevin Nochez
License: MIT License
Classifier: Development Status :: 4 - Beta
Classifier: Intended Audience :: Developers
Classifier: Intended Audience :: Science/Research
Classifier: License :: OSI Approved :: MIT License
Classifier: Programming Language :: Python :: 3
Classifier: Programming Language :: Python :: 3.7
Classifier: Programming Language :: Python :: 3.8
Classifier: Programming Language :: Python :: 3.9
Classifier: Programming Language :: Python :: 3.10
Classifier: Operating System :: OS Independent
Classifier: Topic :: Scientific/Engineering :: Information Analysis
Requires-Python: >=3.7
License-File: LICENSE
Requires-Dist: pandas>=1.3.0
Requires-Dist: numpy>=1.21.0
Requires-Dist: openpyxl>=3.1.0
Dynamic: home-page
Dynamic: license-file
Dynamic: requires-python
